dotenvx/__init__.py
dotenvx/__version__.py
dotenvx/main.py
dotenvx/bin/dotenvx
python_dotenvx-0.3.0.dist-info/licenses/LICENSE
python_dotenvx-0.3.0.dist-info/METADATA
python_dotenvx-0.3.0.dist-info/WHEEL
python_dotenvx-0.3.0.dist-info/entry_points.txt
python_dotenvx-0.3.0.dist-info/top_level.txt
python_dotenvx-0.3.0.dist-info/RECORD
