Metadata-Version: 2.4
Name: python-dotenvx
Version: 0.3.0
Summary: [dotenvx.com] a better dotenv–from the creator of `dotenv`
Home-page: https://github.com/dotenvx/python-dotenvx
Author: dotenv
Author-email: mot@dotenvx.com
License: BSD-3-Clause
Keywords: environment,environment variables,deployments,settings,env,dotenv,configurations,python,dotenvx
License-File: LICENSE
Dynamic: author
Dynamic: author-email
Dynamic: description
Dynamic: description-content-type
Dynamic: home-page
Dynamic: keywords
Dynamic: license
Dynamic: license-file
Dynamic: summary
